cvpm/__init__.py
cvpm/bootstrap.py
cvpm/bundle.py
cvpm/interface.py
cvpm/pipeline.py
cvpm/server.py
cvpm/solver.py
cvpm/utility.py
cvpm-0.0.2.5.dist-info/LICENSE
cvpm-0.0.2.5.dist-info/LICENSE-996-Forbidden
cvpm-0.0.2.5.dist-info/METADATA
cvpm-0.0.2.5.dist-info/WHEEL
cvpm-0.0.2.5.dist-info/top_level.txt
cvpm-0.0.2.5.dist-info/RECORD
