Metadata-Version: 2.1
Name: cvpm
Version: 0.0.2.5
Summary: Computer Vision Package Manager
Home-page: https://cvpm.autoai.org
Author: Xiaozhe Yao
Author-email: xiaozhe.yaoi@gmail.com
License: MIT
Project-URL: Bug Tracker, https://github.com/unarxiv/CVPM/issues
Project-URL: Documentation, https://cvpm.autoai.org
Project-URL: Source Code, https://github.com/unarxiv/CVPM/issues
Platform: UNKNOWN
Classifier: Programming Language :: Python :: 3
Classifier: License :: OSI Approved :: MIT License
Classifier: Operating System :: OS Independent
Classifier: Intended Audience :: Developers
Classifier: Intended Audience :: Education
Classifier: Intended Audience :: Information Technology
Classifier: Intended Audience :: Science/Research
Classifier: Topic :: Scientific/Engineering
Classifier: Topic :: Scientific/Engineering :: Image Recognition
Classifier: Topic :: Software Development
Requires-Dist: flask
Requires-Dist: tqdm
Requires-Dist: toml
Requires-Dist: requests
Requires-Dist: pillow
Requires-Dist: numpy
Requires-Dist: gevent
